cmake_parser/__init__.py
cmake_parser/__main__.py
cmake_parser/_version.py
cmake_parser/ast.py
cmake_parser/error.py
cmake_parser/interpreter.py
cmake_parser/lexer.py
cmake_parser/parser.py
cmake_parser-0.9.2.dist-info/METADATA
cmake_parser-0.9.2.dist-info/WHEEL
cmake_parser-0.9.2.dist-info/top_level.txt
cmake_parser-0.9.2.dist-info/RECORD
