Metadata-Version: 2.1
Name: cmake-parser
Version: 0.9.2
Summary: Pure Python library to parse CMake scripts
Author-email: Timo Röhling <timo@gaussglocke.de>
License: 
Project-URL: GitHub, https://github.com/roehling/cmake_parser
Project-URL: Documentation, https://roehling.github.io/cmake_parser/
Classifier: License :: OSI Approved :: Apache Software License
Classifier: Programming Language :: Python :: 3
Classifier: Operating System :: OS Independent
Requires-Python: >=3.6
Requires-Dist: attrs >=21.3.0
